streamlit_lyrics_sync/__init__.py
streamlit_lyrics_sync/demo.py
streamlit_lyrics_sync/notes.py
streamlit_lyrics_sync/phrase.py
streamlit_lyrics_sync-0.2.0.dist-info/METADATA
streamlit_lyrics_sync-0.2.0.dist-info/WHEEL
streamlit_lyrics_sync-0.2.0.dist-info/top_level.txt
streamlit_lyrics_sync-0.2.0.dist-info/RECORD
