Metadata-Version: 2.4
Name: streamlit_lyrics_sync
Version: 0.2.0
Summary: A compoennt for syncing lyrics to an audio waveform
Home-page: 
Author: Liam Power
Author-email: info@liampower.dev
Requires-Python: >=3.9
Requires-Dist: python-dotenv>=1.1.0
Requires-Dist: requests>=2.32.3
Requires-Dist: setuptools>=75.8.0
Requires-Dist: streamlit>=1.42.0
Dynamic: author
Dynamic: author-email
Dynamic: requires-python
